newtype/__init__.py
newtype/extensions/__init__.py
newtype/extensions/newtype_debug_print.h
newtype/extensions/newtype_init.c
newtype/extensions/newtype_init.h
newtype/extensions/newtype_meth.c
newtype/extensions/newtype_meth.h
newtype/extensions/newtypeinit.cp312-win_amd64.pyd
newtype/extensions/newtypeinit.pyi
newtype/extensions/newtypemethod.cp312-win_amd64.pyd
newtype/extensions/newtypemethod.pyi
newtype/mypy_plugin.py
newtype/newtype.py
newtype/py.typed
python_newtype-0.1.6.dist-info/entry_points.txt
python_newtype-0.1.6.dist-info/LICENSE
python_newtype-0.1.6.dist-info/METADATA
python_newtype-0.1.6.dist-info/WHEEL
python_newtype-0.1.6.dist-info/RECORD
