Metadata-Version: 2.1
Name: python-newtype
Version: 0.1.6
Summary: A Python library for creating and managing new types with enhanced type safety and flexibility.
Home-page: https://github.com/jymchng/python-newtype-dev
License: MIT
Author: Jim Chng
Author-email: jimchng@outlook.com
Requires-Python: >=3.8,<4.0
Classifier: License :: OSI Approved :: MIT License
Classifier: Programming Language :: Python :: 3
Classifier: Programming Language :: Python :: 3.8
Classifier: Programming Language :: Python :: 3.9
Classifier: Programming Language :: Python :: 3.10
Classifier: Programming Language :: Python :: 3.11
Classifier: Programming Language :: Python :: 3.12
Classifier: Programming Language :: Python :: 3.13
Project-URL: Documentation, https://py-nt.asyncmove.com
Project-URL: Repository, https://github.com/jymchng/python-newtype-dev
